elasticConstants/__init__.py
elasticConstants-0.0.3.dist-info/LICENSE
elasticConstants-0.0.3.dist-info/METADATA
elasticConstants-0.0.3.dist-info/WHEEL
elasticConstants-0.0.3.dist-info/top_level.txt
elasticConstants-0.0.3.dist-info/RECORD
