Metadata-Version: 2.1
Name: elasticConstants
Version: 0.0.3
Summary: Convert pair of elastic constants
Home-page: https://github.com/tdegeus/elasticConstants
Author: Tom de Geus
Author-email: tom@geus.me
License: MIT
Keywords: elasticity
Platform: UNKNOWN
